{
	"dataList": [
		{
			"name": "베가",
			"dialogues": 
			{
				"join": [
					{
						"index": "0",
						"text": [
							"......"
						]
					}
				]
			}
		},
		{
			"name": "멜리크",
			"dialogues": 
			{
				"join": [
					{
						"index": "0",
						"text": [
							"......"
						]
					}
				],
				"first": [
					{
						"index": "0",
						"text": [
							"암전 얘기를 꺼내려는 거면 나는 할 얘기 없어.",
							"이 천문대에 있는 걸 보면 너도 암전과 어느 정도 연관이 있는 것 같은데, 네 말을 믿을 수 있다는 근거가 있나?"
						]
					}
				],
				"second": [
					{
						"index": "0",
						"text": [
							"나는 너를 경계할 수밖에 없는 상황이야. 이해해줬으면 좋겠어.", 
							"하지만 암전 이외의 얘기라면.. 땅 위에 있는 사람하고 얘기할 일은 별로 없으니 괜찮겠지.",
							"..너도 다른 천체를 만나봤다면 알겠지만, 땅 위에 있던 시절을 웬만큼은 기억하고 있으니까.",
							"그래도 그때를 회상하는 거랑 다시 그런 순간을 맞는 것은 많이 달라.",
							"땅 위에 있을 때 어땠냐고?", 
							"친한 사람은 많이 없었어. 어렸을 때부터 작업장 같은 곳에 팔려가서 일했고, 주변 사람들은 나를 별로 좋아하지 않았으니까.",
							"다음에 기회가 되면 또 대화하는 것도 나쁘지 않을 것 같네."
						]
					}
				],
				"third": [
					{
						"index": "0",
						"text": [
							"이 물병? 아, 천체가 되기 전부터 술 담그는 게 내 일이었거든. 지금도 이 일을 계속하고 있어.", 
							"아케르는 만나봤으려나? 걔도 내 일을 돕고 있고.",
							"어렸을 때 우울해지면 몰래 밖에 나와서 밤하늘을 구경했거든. 별들을 볼 때마다 누군가 날 위로하는 기분이 들었어.", 
							"지금은 내가 그 위에 있다는 게 웃기지만.", 
							"그래서 예전에는 밤하늘 같은 색을 띠는, 사람을 위로할 수 있는 술을 만들고 싶었어.",
							"너, 이렇게 말을 거는 이유가 암전에 관해서 변명하고 싶은 거지?",
							"설명해줘. 대체 왜 이런 일이 일어났는지.",
							"나에게 생각할 시간을 조금만 줘. 이게 전부 사실이라면.."
						]
					}
				]
			}
		},
		{
			"name": "아케르",
			"dialogues":
			{
				"join": [
					{
						"index": "0",
						"text": [
							"만나서 반가워!"
						]
					}
				],
				"first": [
					{
						"index": "0",
						"text": [
							"안녕!",
							"여자애는 오랜만에 보네. 나랑 비슷해서 좋다.",
							"나는 아케르야. 방금 네가 보던 에리다누스자리에서 왔어. 막 심심해지고 있었는데 이런 새로운 곳을 볼 수 있다니 행운이네.",
							"앞으로도 잘 부탁해."
						]
					}
				],
				"second": [
					{
						"index": "0",
						"text": [
							"혹시 간식 있어?",
							"#응! 사탕, 초콜릿...뭐 좋아해?#음...미안. 지금은 없는 것 같아."
						]
					},
					{
						"index": "1-1",
						"text": [
							"우와, 정말 나 주는거야? 고마워!"
						]
					},
					{
						"index": "1-2",
						"text": [
							"흠, 아쉽다. 혹시 단 거 좋아해?",
							"단 게 먹고 싶은데 별이 되고 나서는 먹기 힘든 것 같아."
						]
					},
					{
						"index": "3",
						"text": [
							"아빠랑 오빠들이 어디 다녀올 때면 간식 같은 거 많이 사 왔었어.",
							"그 때 만났으면 같이 간식 먹으면서 얘기했을 텐데,"
						]
					}
				]
			}
		},
		{
			"name": "안카",
			"dialogues": 
			{
				"join": [
					{
						"index": "0",
						"text": [
							"......"
						]
					}
				]
			}
		},
		{
			"name": "안타레스",
			"dialogues": 
			{
				"join": [
					{
						"index": "0",
						"text": [
							"......"
						]
					}
				]
			}
		},
		{
			"name": "에니프",
			"dialogues": 
			{
				"join": [
					{
						"index": "0",
						"text": [
							"......"
						]
					}
				]
			}
		},
		{
			"name": "폴라리스",
			"dialogues":
			{
				"join": [
					{
						"index": "0",
						"text": [
							"......"
						]
					}
				]
			}
		}
	]
}